LICENSE
README.md
setup.py
bin/bma-benchmark
bma_benchmark/__init__.py
bma_benchmark.egg-info/PKG-INFO
bma_benchmark.egg-info/SOURCES.txt
bma_benchmark.egg-info/dependency_links.txt
bma_benchmark.egg-info/requires.txt
bma_benchmark.egg-info/top_level.txt