Metadata-Version: 2.1
Name: bma-benchmark
Version: 0.0.6
Summary: Python benchmark tool
Home-page: https://github.com/alttch/bma-benchmark-py
Author: Bohemia Automation / Altertech
Author-email: div@altertech.com
License: MIT
Platform: UNKNOWN
Classifier: Programming Language :: Python :: 3
Classifier: License :: OSI Approved :: MIT License
Classifier: Topic :: Software Development :: Libraries
Classifier: Topic :: System :: Benchmark
License-File: LICENSE
